bdilab_detect/README.md
bdilab_detect/__init__.py
bdilab_detect/base.py
bdilab_detect/main.py
bdilab_detect/version.py
bdilab_detect/cd/__init__.py
bdilab_detect/cd/base.py
bdilab_detect/cd/hdddm.py
bdilab_detect/cd/sddm.py
bdilab_detect/cd/utils.py
bdilab_detect/cd/tensorflow/__init__.py
bdilab_detect/cd/tensorflow/preprocess.py
bdilab_detect/cd/tensorflow/sddm.py
bdilab_detect/data/README.md
bdilab_detect/data/elecNormNew.csv
bdilab_detect/data/forestCoverType.csv
bdilab_detect/data/phishing.csv
bdilab_detect/data/benchmark/1CDT.csv
bdilab_detect/data/benchmark/1CHT.csv
bdilab_detect/data/benchmark/1CSurr.txt
bdilab_detect/data/benchmark/2CDT.csv
bdilab_detect/data/benchmark/2CHT.csv
bdilab_detect/data/benchmark/4CE1CF.csv
bdilab_detect/data/benchmark/4CR.csv
bdilab_detect/data/benchmark/4CRE-V1.csv
bdilab_detect/data/benchmark/4CRE-V2.txt
bdilab_detect/data/benchmark/5CVT.csv
bdilab_detect/data/benchmark/FG_2C_2D.txt
bdilab_detect/data/benchmark/GEARS_2C_2D.txt
bdilab_detect/data/benchmark/MG_2C_2D.csv
bdilab_detect/data/benchmark/UG_2C_2D.csv
bdilab_detect/data/benchmark/UG_2C_3D.txt
bdilab_detect/data/benchmark/UG_2C_5D.txt
bdilab_detect/data/benchmark/keystroke.txt
bdilab_detect/data/bike_share/test.csv
bdilab_detect/data/bike_share/train.csv
bdilab_detect/data/weather/NEweather_class.csv
bdilab_detect/data/weather/NEweather_data.csv
bdilab_detect/models/__init__.py
bdilab_detect/models/tensorflow/__init__.py
bdilab_detect/models/tensorflow/embedding.py
bdilab_detect/saving/.DS_Store
bdilab_detect/saving/__init__.py
bdilab_detect/saving/_typing.py
bdilab_detect/saving/loading.py
bdilab_detect/saving/saving.py
bdilab_detect/saving/_tensorflow/__init__.py
bdilab_detect/saving/_tensorflow/loading.py
bdilab_detect/saving/_tensorflow/saving.py
bdilab_detect/saving/test/__init__.py
bdilab_detect/saving/test/save_and_load_test.py
bdilab_detect/saving/test/save_sddm.py
bdilab_detect/saving/test/dill_file/HDDDMDrift.dill
bdilab_detect/saving/test/dill_file/meta.dill
bdilab_detect-0.2.7.dev0.dist-info/LICENSE.txt
bdilab_detect-0.2.7.dev0.dist-info/METADATA
bdilab_detect-0.2.7.dev0.dist-info/WHEEL
bdilab_detect-0.2.7.dev0.dist-info/entry_points.txt
bdilab_detect-0.2.7.dev0.dist-info/top_level.txt
bdilab_detect-0.2.7.dev0.dist-info/RECORD
